networkscaleup/__init__.py
networkscaleup/cmdstan_utils.py
networkscaleup/correlatedStan.py
networkscaleup/killworth.py
networkscaleup/overdispersed.py
networkscaleup/overdispersedStan.py
networkscaleup/scaling.py
networkscaleup/stan/Correlated_basic
networkscaleup/stan/Correlated_basic.stan
networkscaleup/stan/Correlated_x.stan
networkscaleup/stan/Correlated_x_zglobal.stan
networkscaleup/stan/Correlated_x_zsubpop.stan
networkscaleup/stan/Correlated_x_zsubpop_zglobal
networkscaleup/stan/Correlated_x_zsubpop_zglobal.stan
networkscaleup/stan/Correlated_zglobal.stan
networkscaleup/stan/Correlated_zsubpop.stan
networkscaleup/stan/Correlated_zsubpop_zglobal.stan
networkscaleup/stan/Overdispersed_Stan
networkscaleup/stan/Overdispersed_Stan.stan
networkscaleup/stan/Uncorrelated_basic.stan
networkscaleup/stan/Uncorrelated_x.stan
networkscaleup/stan/Uncorrelated_x_zglobal.stan
networkscaleup/stan/Uncorrelated_x_zsubpop.stan
networkscaleup/stan/Uncorrelated_x_zsubpop_zglobal.stan
networkscaleup/stan/Uncorrelated_zglobal.stan
networkscaleup/stan/Uncorrelated_zsubpop.stan
networkscaleup/stan/Uncorrelated_zsubpop_zglobal.stan
networkscaleup/stan/include/license.stan
networkscaleup-0.0.11.dist-info/METADATA
networkscaleup-0.0.11.dist-info/WHEEL
networkscaleup-0.0.11.dist-info/RECORD
