Metadata-Version: 2.4
Name: networkscaleup
Version: 0.0.11
Summary: Network Scale-Up Models for Aggregated Relational Data
Project-URL: Homepage, https://github.com/pypa/sampleproject
Project-URL: Issues, https://github.com/pypa/sampleproject/issues
Author-email: "Ian Laga, Sarah Nagy, Charles Costanzo" <ian.laga@montana.edu>, Charles Costanzo <cgc5478@psu.edu>, Sarah Nagy <s.nagy.4343@gmail.com>
License-Expression: MIT
Keywords: ARD,Bayesian,network scale-up,social networks
Classifier: Operating System :: OS Independent
Classifier: Programming Language :: Python :: 3
Requires-Python: >=3.8
Requires-Dist: cmdstanpy>=1.1
Requires-Dist: numpy>=1.24
Requires-Dist: pandas>=2.1
Requires-Dist: scipy>=1.11
